sar_logic.v
module sar_logic (
    input  wire        clk,           // Clock
    input  wire        rst_n,         // Active-low Reset
    input  wire        comparator_out,// Comparator output (0 or 1)
    output reg  [7:0]  D,             // DAC output code
    output reg         sample_clk,    // Sample & Hold enable
    output reg         reg_clk,       // Latch Register enable
    output reg         EOC            // End Of Conversion
);

    reg [3:0] counter;      // Count 0 -> 9 (sampling + 8 bits + latch) Đếm từ 0 → 9 (1 sample + 8 bits + 1 latch)
    reg [7:0] seq;          // Sequencer to shift active bit Dịch từ MSB → LSB để tạo mã điều khiển DAC


    // Reset & Initial State
    always @(posedge clk or negedge rst_n) begin
        if (!rst_n) begin // rst_n = 0 -> he thong can tro lai trang thai ban dau 
            counter     <= 0;
            seq         <= 8'b1000_0000; // msb -> lsb 
            D           <= 8'b0000_0000; // dac se xuat ra min khi bat dau so sanh (reset dau ra cua dac)
            sample_clk  <= 1'b1;   // First cycle is for sampling // tin hieu de mach sample and hold bat dau lay mau analog
            reg_clk     <= 1'b0; // reg_clock = 0 (dang o trang thai reset)
            EOC         <= 1'b0; // EOC = 0 // chua ket thuc qua trinh chuyen doi 
        end else begin
            case (counter)
                0: begin
                    sample_clk <= 1'b1; // Sampling phase
                    reg_clk    <= 1'b0;
                    D          <= 8'b0000_0000;
                    seq        <= 8'b1000_0000;
                    counter    <= counter + 1;
                    EOC        <= 0;
                end

                1,2,3,4,5,6,7,8: begin
                    sample_clk <= 1'b0;
                    D <= (D & ~seq) | (comparator_out ? seq : 8'b0);
                    seq <= seq >> 1;
                    counter <= counter + 1;
                    reg_clk <= 0;
                    EOC <= 0;
                end

                9: begin
                    reg_clk <= 1;
                    EOC     <= 1;   // End of conversion
                    counter <= 0;   // Ready for next conversion
                end
            endcase
        end
    end

endmodule

Test_bench.v
`timescale 1ns / 1ps

module sar_tb;

    reg clk;
    reg rst_n;
    reg comparator_out;
    wire [7:0] D;
    wire sample_clk;
    wire reg_clk;
    wire EOC;

    // Kết nối DUT (Device Under Test)
    sar_logic uut (
        .clk(clk),
        .rst_n(rst_n),
        .comparator_out(comparator_out),
        .D(D),
        .sample_clk(sample_clk),
        .reg_clk(reg_clk),
        .EOC(EOC)
    );

    // Clock 100MHz
    initial begin
        clk = 0;
        forever #5 clk = ~clk;
    end

    // Reset sequence
    initial begin
        rst_n = 0;
        #20;
        rst_n = 1;
    end

    // Tạo comparator_out ngẫu nhiên
    always @(posedge clk) begin
        comparator_out <= $random % 2;
    end

    // Dump file cho GTKWave
    initial begin
        $dumpfile("sar.vcd");
        $dumpvars(0, sar_tb);
        #500 $finish;
    end

endmodule

sar.vcd
$date
	Mon Jul 14 10:32:09 2025
$end
$version
	Icarus Verilog
$end
$timescale
	1ps
$end
$scope module sar_tb $end
$var wire 1 ! sample_clk $end
$var wire 1 " reg_clk $end
$var wire 1 # EOC $end
$var wire 8 $ D [7:0] $end
$var reg 1 % clk $end
$var reg 1 & comparator_out $end
$var reg 1 ' rst_n $end
$scope module uut $end
$var wire 1 % clk $end
$var wire 1 & comparator_out $end
$var wire 1 ' rst_n $end
$var reg 8 ( D [7:0] $end
$var reg 1 # EOC $end
$var reg 4 ) counter [3:0] $end
$var reg 1 " reg_clk $end
$var reg 1 ! sample_clk $end
$var reg 8 * seq [7:0] $end
$upscope $end
$upscope $end
$enddefinitions $end
#0
$dumpvars
b10000000 *
b0 )
b0 (
0'
x&
0%
b0 $
0#
0"
1!
$end
#5000
0&
1%
#10000
0%
#15000
1&
1%
#20000
0%
1'
#25000
b1 )
1%
#30000
0%
#35000
b10 )
b1000000 *
b10000000 $
b10000000 (
0!
1%
#40000
0%
#45000
b11 )
b100000 *
b11000000 $
b11000000 (
1%
#50000
0%
#55000
b100 )
b10000 *
b11100000 $
b11100000 (
1%
#60000
0%
#65000
b101 )
b1000 *
b11110000 $
b11110000 (
1%
#70000
0%
#75000
b110 )
b100 *
b11111000 $
b11111000 (
0&
1%
#80000
0%
#85000
b111 )
b10 *
1&
1%
#90000
0%
#95000
b1000 )
b1 *
b11111010 $
b11111010 (
1%
#100000
0%
#105000
b1001 )
b0 *
b11111011 $
b11111011 (
0&
1%
#110000
0%
#115000
b0 )
1#
1"
1&
1%
#120000
0%
#125000
0#
b1 )
b10000000 *
b0 $
b0 (
0"
1!
1%
#130000
0%
#135000
b10 )
b1000000 *
b10000000 $
b10000000 (
0!
0&
1%
#140000
0%
#145000
b11 )
b100000 *
1&
1%
#150000
0%
#155000
b100 )
b10000 *
b10100000 $
b10100000 (
0&
1%
#160000
0%
#165000
b101 )
b1000 *
1&
1%
#170000
0%
#175000
b110 )
b100 *
b10101000 $
b10101000 (
0&
1%
#180000
0%
#185000
b111 )
b10 *
1&
1%
#190000
0%
#195000
b1000 )
b1 *
b10101010 $
b10101010 (
1%
#200000
0%
#205000
b1001 )
b0 *
b10101011 $
b10101011 (
0&
1%
#210000
0%
#215000
b0 )
1#
1"
1&
1%
#220000
0%
#225000
0#
b1 )
b10000000 *
b0 $
b0 (
0"
1!
0&
1%
#230000
0%
#235000
b10 )
b1000000 *
0!
1%
#240000
0%
#245000
b11 )
b100000 *
1%
#250000
0%
#255000
b100 )
b10000 *
1&
1%
#260000
0%
#265000
b101 )
b1000 *
b10000 $
b10000 (
0&
1%
#270000
0%
#275000
b110 )
b100 *
1&
1%
#280000
0%
#285000
b111 )
b10 *
b10100 $
b10100 (
1%
#290000
0%
#295000
b1000 )
b1 *
b10110 $
b10110 (
1%
#300000
0%
#305000
b1001 )
b0 *
b10111 $
b10111 (
1%
#310000
0%
#315000
b0 )
1#
1"
0&
1%
#320000
0%
#325000
0#
b1 )
b10000000 *
b0 $
b0 (
0"
1!
1%
#330000
0%
#335000
b10 )
b1000000 *
0!
1%
#340000
0%
#345000
b11 )
b100000 *
1%
#350000
0%
#355000
b100 )
b10000 *
1&
1%
#360000
0%
#365000
b101 )
b1000 *
b10000 $
b10000 (
0&
1%
#370000
0%
#375000
b110 )
b100 *
1&
1%
#380000
0%
#385000
b111 )
b10 *
b10100 $
b10100 (
1%
#390000
0%
#395000
b1000 )
b1 *
b10110 $
b10110 (
1%
#400000
0%
#405000
b1001 )
b0 *
b10111 $
b10111 (
1%
#410000
0%
#415000
b0 )
1#
1"
1%
#420000
0%
#425000
0#
b1 )
b10000000 *
b0 $
b0 (
0"
1!
0&
1%
#430000
0%
#435000
b10 )
b1000000 *
0!
1%
#440000
0%
#445000
b11 )
b100000 *
1&
1%
#450000
0%
#455000
b100 )
b10000 *
b100000 $
b100000 (
1%
#460000
0%
#465000
b101 )
b1000 *
b110000 $
b110000 (
1%
#470000
0%
#475000
b110 )
b100 *
b111000 $
b111000 (
0&
1%
#480000
0%
#485000
b111 )
b10 *
1%
#490000
0%
#495000
b1000 )
b1 *
1%
