sar_logic.v
module sar_logic_10bit (
    input  wire         clk,            // Clock
    input  wire         rst_n,          // Active-low Reset
    input  wire         comparator_out, // Comparator output (0 or 1)
    output reg  [9:0]   D,              // DAC output code (10-bit)
    output reg          sample_clk,     // Sample & Hold enable
    output reg          reg_clk,        // Latch Register enable
    output reg          EOC             // End Of Conversion
);

    reg [3:0] counter;    // Count 0 -> 11 (sampling + 10 bits + latch)
    reg [9:0] seq;        // Sequencer 10-bit MSB -> LSB

    // Reset & Initial State
    always @(posedge clk or negedge rst_n) begin
        if (!rst_n) begin
            counter     <= 0;
            seq         <= 10'b1000_0000_00; // Start from MSB (bit 9)
            D           <= 10'b0000_0000_00;
            sample_clk  <= 1'b1;
            reg_clk     <= 1'b0;
            EOC         <= 1'b0;
        end else begin
            case (counter)
                0: begin
                    sample_clk <= 1'b1; 
                    reg_clk    <= 1'b0;
                    D          <= 10'b0000_0000_00;
                    seq        <= 10'b1000_0000_00;
                    counter    <= counter + 1;
                    EOC        <= 0;
                end

                1,2,3,4,5,6,7,8,9,10: begin
                    sample_clk <= 1'b0;
                    D <= (D & ~seq) | (comparator_out ? seq : 10'b0);
                    seq <= seq >> 1;
                    counter <= counter + 1;
                    reg_clk <= 0;
                    EOC <= 0;
                end

                11: begin
                    reg_clk <= 1;
                    EOC     <= 1;   // End of conversion
                    counter <= 0;   // Ready for next conversion
                end
            endcase
        end
    end

endmodule

Test_bench.v
`timescale 1ns / 1ps

module sar_tb;

    reg clk;
    reg rst_n;
    reg comparator_out;
    wire [9:0] D;          
    wire sample_clk;
    wire reg_clk;
    wire EOC;

    // Kết nối DUT (Device Under Test) - 10-bit SAR Logic
    sar_logic_10bit uut (
        .clk(clk),
        .rst_n(rst_n),
        .comparator_out(comparator_out),
        .D(D),
        .sample_clk(sample_clk),
        .reg_clk(reg_clk),
        .EOC(EOC)
    );

    // Tạo xung clock 100MHz (10ns period)
    initial begin
        clk = 0;
        forever #5 clk = ~clk;
    end

    // Reset sequence
    initial begin
        rst_n = 0;
        #20;
        rst_n = 1;
    end

    // Giả lập comparator_out ngẫu nhiên
    always @(posedge clk) begin
        comparator_out <= $random % 2;
    end

    // Tạo file VCD để xem bằng GTKWave
    initial begin
        $dumpfile("sar.vcd");
        $dumpvars(0, sar_tb);
        #2000 $finish;
    end

endmodule

sar.vcd
$date
	Wed Jul 16 10:46:21 2025
$end
$version
	Icarus Verilog
$end
$timescale
	1ps
$end
$scope module sar_tb $end
$var wire 1 ! sample_clk $end
$var wire 1 " reg_clk $end
$var wire 1 # EOC $end
$var wire 10 $ D [9:0] $end
$var reg 1 % clk $end
$var reg 1 & comparator_out $end
$var reg 1 ' rst_n $end
$scope module uut $end
$var wire 1 % clk $end
$var wire 1 & comparator_out $end
$var wire 1 ' rst_n $end
$var reg 10 ( D [9:0] $end
$var reg 1 # EOC $end
$var reg 4 ) counter [3:0] $end
$var reg 1 " reg_clk $end
$var reg 1 ! sample_clk $end
$var reg 10 * seq [9:0] $end
$upscope $end
$upscope $end
$enddefinitions $end
#0
$dumpvars
b1000000000 *
b0 )
b0 (
0'
x&
0%
b0 $
0#
0"
1!
$end
#5000
0&
1%
#10000
0%
#15000
1&
1%
#20000
0%
1'
#25000
b1 )
1%
#30000
0%
#35000
b10 )
b100000000 *
b1000000000 $
b1000000000 (
0!
1%
#40000
0%
#45000
b11 )
b10000000 *
b1100000000 $
b1100000000 (
1%
#50000
0%
#55000
b100 )
b1000000 *
b1110000000 $
b1110000000 (
1%
#60000
0%
#65000
b101 )
b100000 *
b1111000000 $
b1111000000 (
1%
#70000
0%
#75000
b110 )
b10000 *
b1111100000 $
b1111100000 (
0&
1%
#80000
0%
#85000
b111 )
b1000 *
1&
1%
#90000
0%
#95000
b1000 )
b100 *
b1111101000 $
b1111101000 (
1%
#100000
0%
#105000
b1001 )
b10 *
b1111101100 $
b1111101100 (
0&
1%
#110000
0%
#115000
b1010 )
b1 *
1&
1%
#120000
0%
#125000
b1011 )
b0 *
b1111101101 $
b1111101101 (
1%
#130000
0%
#135000
b0 )
1#
1"
0&
1%
#140000
0%
#145000
0#
b1 )
b1000000000 *
b0 $
b0 (
0"
1!
1&
1%
#150000
0%
#155000
b10 )
b100000000 *
b1000000000 $
b1000000000 (
0!
0&
1%
#160000
0%
#165000
b11 )
b10000000 *
1&
1%
#170000
0%
#175000
b100 )
b1000000 *
b1010000000 $
b1010000000 (
0&
1%
#180000
0%
#185000
b101 )
b100000 *
1&
1%
#190000
0%
#195000
b110 )
b10000 *
b1010100000 $
b1010100000 (
1%
#200000
0%
#205000
b111 )
b1000 *
b1010110000 $
b1010110000 (
0&
1%
#210000
0%
#215000
b1000 )
b100 *
1&
1%
#220000
0%
#225000
b1001 )
b10 *
b1010110100 $
b1010110100 (
0&
1%
#230000
0%
#235000
b1010 )
b1 *
1%
#240000
0%
#245000
b1011 )
b0 *
1%
#250000
0%
#255000
b0 )
1#
1"
1&
1%
#260000
0%
#265000
0#
b1 )
b1000000000 *
b0 $
b0 (
0"
1!
0&
1%
#270000
0%
#275000
b10 )
b100000000 *
0!
1&
1%
#280000
0%
#285000
b11 )
b10000000 *
b100000000 $
b100000000 (
1%
#290000
0%
#295000
b100 )
b1000000 *
b110000000 $
b110000000 (
1%
#300000
0%
#305000
b101 )
b100000 *
b111000000 $
b111000000 (
1%
#310000
0%
#315000
b110 )
b10000 *
b111100000 $
b111100000 (
0&
1%
#320000
0%
#325000
b111 )
b1000 *
1%
#330000
0%
#335000
b1000 )
b100 *
1%
#340000
0%
#345000
b1001 )
b10 *
1%
#350000
0%
#355000
b1010 )
b1 *
1&
1%
#360000
0%
#365000
b1011 )
b0 *
b111100001 $
b111100001 (
0&
1%
#370000
0%
#375000
b0 )
1#
1"
1&
1%
#380000
0%
#385000
0#
b1 )
b1000000000 *
b0 $
b0 (
0"
1!
1%
#390000
0%
#395000
b10 )
b100000000 *
b1000000000 $
b1000000000 (
0!
1%
#400000
0%
#405000
b11 )
b10000000 *
b1100000000 $
b1100000000 (
1%
#410000
0%
#415000
b100 )
b1000000 *
b1110000000 $
b1110000000 (
1%
#420000
0%
#425000
b101 )
b100000 *
b1111000000 $
b1111000000 (
0&
1%
#430000
0%
#435000
b110 )
b10000 *
1%
#440000
0%
#445000
b111 )
b1000 *
1&
1%
#450000
0%
#455000
b1000 )
b100 *
b1111001000 $
b1111001000 (
1%
#460000
0%
#465000
b1001 )
b10 *
b1111001100 $
b1111001100 (
1%
#470000
0%
#475000
b1010 )
b1 *
b1111001110 $
b1111001110 (
0&
1%
#480000
0%
#485000
b1011 )
b0 *
1%
#490000
0%
#495000
b0 )
1#
1"
1%
#500000
0%
#505000
0#
b1 )
b1000000000 *
b0 $
b0 (
0"
1!
1%
#510000
0%
#515000
b10 )
b100000000 *
0!
1%
#520000
0%
#525000
b11 )
b10000000 *
1&
1%
#530000
0%
#535000
b100 )
b1000000 *
b10000000 $
b10000000 (
0&
1%
#540000
0%
#545000
b101 )
b100000 *
1%
#550000
0%
#555000
b110 )
b10000 *
1&
1%
#560000
0%
#565000
b111 )
b1000 *
b10010000 $
b10010000 (
1%
#570000
0%
#575000
b1000 )
b100 *
b10011000 $
b10011000 (
0&
1%
#580000
0%
#585000
b1001 )
b10 *
1%
#590000
0%
#595000
b1010 )
b1 *
1%
#600000
0%
#605000
b1011 )
b0 *
1%
#610000
0%
#615000
b0 )
1#
1"
1%
#620000
0%
#625000
0#
b1 )
b1000000000 *
b0 $
b0 (
0"
1!
1&
1%
#630000
0%
#635000
b10 )
b100000000 *
b1000000000 $
b1000000000 (
0!
1%
#640000
0%
#645000
b11 )
b10000000 *
b1100000000 $
b1100000000 (
1%
#650000
0%
#655000
b100 )
b1000000 *
b1110000000 $
b1110000000 (
1%
#660000
0%
#665000
b101 )
b100000 *
b1111000000 $
b1111000000 (
1%
#670000
0%
#675000
b110 )
b10000 *
b1111100000 $
b1111100000 (
0&
1%
#680000
0%
#685000
b111 )
b1000 *
1%
#690000
0%
#695000
b1000 )
b100 *
1&
1%
#700000
0%
#705000
b1001 )
b10 *
b1111100100 $
b1111100100 (
1%
#710000
0%
#715000
b1010 )
b1 *
b1111100110 $
b1111100110 (
1%
#720000
0%
#725000
b1011 )
b0 *
b1111100111 $
b1111100111 (
0&
1%
#730000
0%
#735000
b0 )
1#
1"
1%
#740000
0%
#745000
0#
b1 )
b1000000000 *
b0 $
b0 (
0"
1!
1&
1%
#750000
0%
#755000
b10 )
b100000000 *
b1000000000 $
b1000000000 (
0!
1%
#760000
0%
#765000
b11 )
b10000000 *
b1100000000 $
b1100000000 (
0&
1%
#770000
0%
#775000
b100 )
b1000000 *
1&
1%
#780000
0%
#785000
b101 )
b100000 *
b1101000000 $
b1101000000 (
1%
#790000
0%
#795000
b110 )
b10000 *
b1101100000 $
b1101100000 (
0&
1%
#800000
0%
#805000
b111 )
b1000 *
1&
1%
#810000
0%
#815000
b1000 )
b100 *
b1101101000 $
b1101101000 (
1%
#820000
0%
#825000
b1001 )
b10 *
b1101101100 $
b1101101100 (
1%
#830000
0%
#835000
b1010 )
b1 *
b1101101110 $
b1101101110 (
0&
1%
#840000
0%
#845000
b1011 )
b0 *
1&
1%
#850000
0%
#855000
b0 )
1#
1"
1%
#860000
0%
#865000
0#
b1 )
b1000000000 *
b0 $
b0 (
0"
1!
0&
1%
#870000
0%
#875000
b10 )
b100000000 *
0!
1%
#880000
0%
#885000
b11 )
b10000000 *
1%
#890000
0%
#895000
b100 )
b1000000 *
1%
#900000
0%
#905000
b101 )
b100000 *
1&
1%
#910000
0%
#915000
b110 )
b10000 *
b100000 $
b100000 (
1%
#920000
0%
#925000
b111 )
b1000 *
b110000 $
b110000 (
0&
1%
#930000
0%
#935000
b1000 )
b100 *
1%
#940000
0%
#945000
b1001 )
b10 *
1&
1%
#950000
0%
#955000
b1010 )
b1 *
b110010 $
b110010 (
1%
#960000
0%
#965000
b1011 )
b0 *
b110011 $
b110011 (
1%
#970000
0%
#975000
b0 )
1#
1"
1%
#980000
0%
#985000
0#
b1 )
b1000000000 *
b0 $
b0 (
0"
1!
1%
#990000
0%
#995000
b10 )
b100000000 *
b1000000000 $
b1000000000 (
0!
0&
1%
#1000000
0%
#1005000
b11 )
b10000000 *
1&
1%
#1010000
0%
#1015000
b100 )
b1000000 *
b1010000000 $
b1010000000 (
1%
#1020000
0%
#1025000
b101 )
b100000 *
b1011000000 $
b1011000000 (
1%
#1030000
0%
#1035000
b110 )
b10000 *
b1011100000 $
b1011100000 (
0&
1%
#1040000
0%
#1045000
b111 )
b1000 *
1%
#1050000
0%
#1055000
b1000 )
b100 *
1%
#1060000
0%
#1065000
b1001 )
b10 *
1%
#1070000
0%
#1075000
b1010 )
b1 *
1%
#1080000
0%
#1085000
b1011 )
b0 *
1%
#1090000
0%
#1095000
b0 )
1#
1"
1%
#1100000
0%
#1105000
0#
b1 )
b1000000000 *
b0 $
b0 (
0"
1!
1&
1%
#1110000
0%
#1115000
b10 )
b100000000 *
b1000000000 $
b1000000000 (
0!
1%
#1120000
0%
#1125000
b11 )
b10000000 *
b1100000000 $
b1100000000 (
1%
#1130000
0%
#1135000
b100 )
b1000000 *
b1110000000 $
b1110000000 (
1%
#1140000
0%
#1145000
b101 )
b100000 *
b1111000000 $
b1111000000 (
1%
#1150000
0%
#1155000
b110 )
b10000 *
b1111100000 $
b1111100000 (
0&
1%
#1160000
0%
#1165000
b111 )
b1000 *
1&
1%
#1170000
0%
#1175000
b1000 )
b100 *
b1111101000 $
b1111101000 (
1%
#1180000
0%
#1185000
b1001 )
b10 *
b1111101100 $
b1111101100 (
0&
1%
#1190000
0%
#1195000
b1010 )
b1 *
1%
#1200000
0%
#1205000
b1011 )
b0 *
1&
1%
#1210000
0%
#1215000
b0 )
1#
1"
1%
#1220000
0%
#1225000
0#
b1 )
b1000000000 *
b0 $
b0 (
0"
1!
0&
1%
#1230000
0%
#1235000
b10 )
b100000000 *
0!
1&
1%
#1240000
0%
#1245000
b11 )
b10000000 *
b100000000 $
b100000000 (
1%
#1250000
0%
#1255000
b100 )
b1000000 *
b110000000 $
b110000000 (
1%
#1260000
0%
#1265000
b101 )
b100000 *
b111000000 $
b111000000 (
1%
#1270000
0%
#1275000
b110 )
b10000 *
b111100000 $
b111100000 (
0&
1%
#1280000
0%
#1285000
b111 )
b1000 *
1%
#1290000
0%
#1295000
b1000 )
b100 *
1%
#1300000
0%
#1305000
b1001 )
b10 *
1&
1%
#1310000
0%
#1315000
b1010 )
b1 *
b111100010 $
b111100010 (
0&
1%
#1320000
0%
#1325000
b1011 )
b0 *
1%
#1330000
0%
#1335000
b0 )
1#
1"
1%
#1340000
0%
#1345000
0#
b1 )
b1000000000 *
b0 $
b0 (
0"
1!
1&
1%
#1350000
0%
#1355000
b10 )
b100000000 *
b1000000000 $
b1000000000 (
0!
1%
#1360000
0%
#1365000
b11 )
b10000000 *
b1100000000 $
b1100000000 (
0&
1%
#1370000
0%
#1375000
b100 )
b1000000 *
1%
#1380000
0%
#1385000
b101 )
b100000 *
1&
1%
#1390000
0%
#1395000
b110 )
b10000 *
b1100100000 $
b1100100000 (
0&
1%
#1400000
0%
#1405000
b111 )
b1000 *
1%
#1410000
0%
#1415000
b1000 )
b100 *
1%
#1420000
0%
#1425000
b1001 )
b10 *
1&
1%
#1430000
0%
#1435000
b1010 )
b1 *
b1100100010 $
b1100100010 (
0&
1%
#1440000
0%
#1445000
b1011 )
b0 *
1%
#1450000
0%
#1455000
b0 )
1#
1"
1&
1%
#1460000
0%
#1465000
0#
b1 )
b1000000000 *
b0 $
b0 (
0"
1!
0&
1%
#1470000
0%
#1475000
b10 )
b100000000 *
0!
1&
1%
#1480000
0%
#1485000
b11 )
b10000000 *
b100000000 $
b100000000 (
1%
#1490000
0%
#1495000
b100 )
b1000000 *
b110000000 $
b110000000 (
1%
#1500000
0%
#1505000
b101 )
b100000 *
b111000000 $
b111000000 (
1%
#1510000
0%
#1515000
b110 )
b10000 *
b111100000 $
b111100000 (
1%
#1520000
0%
#1525000
b111 )
b1000 *
b111110000 $
b111110000 (
0&
1%
#1530000
0%
#1535000
b1000 )
b100 *
1%
#1540000
0%
#1545000
b1001 )
b10 *
1%
#1550000
0%
#1555000
b1010 )
b1 *
1&
1%
#1560000
0%
#1565000
b1011 )
b0 *
b111110001 $
b111110001 (
0&
1%
#1570000
0%
#1575000
b0 )
1#
1"
1%
#1580000
0%
#1585000
0#
b1 )
b1000000000 *
b0 $
b0 (
0"
1!
1&
1%
#1590000
0%
#1595000
b10 )
b100000000 *
b1000000000 $
b1000000000 (
0!
1%
#1600000
0%
#1605000
b11 )
b10000000 *
b1100000000 $
b1100000000 (
0&
1%
#1610000
0%
#1615000
b100 )
b1000000 *
1%
#1620000
0%
#1625000
b101 )
b100000 *
1%
#1630000
0%
#1635000
b110 )
b10000 *
1&
1%
#1640000
0%
#1645000
b111 )
b1000 *
b1100010000 $
b1100010000 (
1%
#1650000
0%
#1655000
b1000 )
b100 *
b1100011000 $
b1100011000 (
0&
1%
#1660000
0%
#1665000
b1001 )
b10 *
1%
#1670000
0%
#1675000
b1010 )
b1 *
1%
#1680000
0%
#1685000
b1011 )
b0 *
1&
1%
#1690000
0%
#1695000
b0 )
1#
1"
1%
#1700000
0%
#1705000
0#
b1 )
b1000000000 *
b0 $
b0 (
0"
1!
0&
1%
#1710000
0%
#1715000
b10 )
b100000000 *
0!
1%
#1720000
0%
#1725000
b11 )
b10000000 *
1%
#1730000
0%
#1735000
b100 )
b1000000 *
1&
1%
#1740000
0%
#1745000
b101 )
b100000 *
b1000000 $
b1000000 (
0&
1%
#1750000
0%
#1755000
b110 )
b10000 *
1%
#1760000
0%
#1765000
b111 )
b1000 *
1&
1%
#1770000
0%
#1775000
b1000 )
b100 *
b1001000 $
b1001000 (
0&
1%
#1780000
0%
#1785000
b1001 )
b10 *
1%
#1790000
0%
#1795000
b1010 )
b1 *
1%
#1800000
0%
#1805000
b1011 )
b0 *
1&
1%
#1810000
0%
#1815000
b0 )
1#
1"
0&
1%
#1820000
0%
#1825000
0#
b1 )
b1000000000 *
b0 $
b0 (
0"
1!
1&
1%
#1830000
0%
#1835000
b10 )
b100000000 *
b1000000000 $
b1000000000 (
0!
1%
#1840000
0%
#1845000
b11 )
b10000000 *
b1100000000 $
b1100000000 (
0&
1%
#1850000
0%
#1855000
b100 )
b1000000 *
1%
#1860000
0%
#1865000
b101 )
b100000 *
1%
#1870000
0%
#1875000
b110 )
b10000 *
1%
#1880000
0%
#1885000
b111 )
b1000 *
1&
1%
#1890000
0%
#1895000
b1000 )
b100 *
b1100001000 $
b1100001000 (
0&
1%
#1900000
0%
#1905000
b1001 )
b10 *
1%
#1910000
0%
#1915000
b1010 )
b1 *
1%
#1920000
0%
#1925000
b1011 )
b0 *
1%
#1930000
0%
#1935000
b0 )
1#
1"
1&
1%
#1940000
0%
#1945000
0#
b1 )
b1000000000 *
b0 $
b0 (
0"
1!
1%
#1950000
0%
#1955000
b10 )
b100000000 *
b1000000000 $
b1000000000 (
0!
1%
#1960000
0%
#1965000
b11 )
b10000000 *
b1100000000 $
b1100000000 (
0&
1%
#1970000
0%
#1975000
b100 )
b1000000 *
1&
1%
#1980000
0%
#1985000
b101 )
b100000 *
b1101000000 $
b1101000000 (
1%
#1990000
0%
#1995000
b110 )
b10000 *
b1101100000 $
b1101100000 (
1%
