verilog/rtl/adc_control_nonbinary.v
//  Copyright 2022 Manuel Moser
//
//   Licensed under the Apache License, Version 2.0 (the "License");
//   you may not use this file except in compliance with the License.
//   You may obtain a copy of the License at
//
//       http://www.apache.org/licenses/LICENSE-2.0
//
//   Unless required by applicable law or agreed to in writing, software
//   distributed under the License is distributed on an "AS IS" BASIS,
//   WITHOUT WARRANTIES OR CONDITIONS OF ANY KIND, either express or implied.
//   See the License for the specific language governing permissions and
//   limitations under the License.
`default_nettype none

module adc_control_nonbinary #(
    parameter MATRIX_BITS = 10,
    parameter NONBINARY_REDUNDANCY = 3
)(
   input wire clk,
   input wire rst_n,
   input wire comparator_in,
   input wire [2:0] avg_control_in,
   output wire sample_out,
   output wire sample_out_n,
   output wire enable_loop_out,
   output wire conv_finished_strobe_out,
   output wire [MATRIX_BITS-1:0] pswitch_out,
   output wire [MATRIX_BITS-1:0] nswitch_out,
   output reg [MATRIX_BITS-1:0] result_out
);
   
   // Internal registers
   reg [MATRIX_BITS + NONBINARY_REDUNDANCY + 1 : 0] shift_register_r;
   reg [MATRIX_BITS-1:0] data_register_r;
   reg [4:0] average_counter_r;
   reg [4:0] average_sum_r;
   reg [2:0] sampled_avg_control_r;
   reg conv_finished_r;

   // Combinatorial signals
   wire [MATRIX_BITS-1:0] next_result_w;
   wire [4:0] next_average_counter_w;
   wire [4:0] next_average_sum_w;
   wire [2:0] next_sampled_avg_control_w;
   wire [MATRIX_BITS + NONBINARY_REDUNDANCY + 1 : 0] next_shift_register_w;
   wire [MATRIX_BITS-1:0] next_data_register_w;

   // LSB region detection (for averaging)
   wire lsb_region_w = (shift_register_r[2] | shift_register_r[3] | shift_register_r[4]);
   wire is_averaging_w = (lsb_region_w && (average_counter_r < average_count_limit_w));
   wire [4:0] average_count_limit_w;
   wire averaged_comparator_in_w;

   // State machine states
   wire is_holding_result_w = shift_register_r[1];
   wire is_sampling_w       = shift_register_r[0];
   wire result_ready_w      = (shift_register_r[2] == 1'b1) && ~is_averaging_w;
   wire result_strobe_w     = (shift_register_r[1] == 1'b1) && ~is_averaging_w;

   //******************************************
   //   Synchronous process and Reset Handling
   //******************************************
   always @(posedge clk or negedge rst_n) begin
      if (!rst_n) begin
         result_out            <= {MATRIX_BITS{1'b0}};
         shift_register_r      <= {{(MATRIX_BITS+NONBINARY_REDUNDANCY+1){1'b0}}, 1'b1};
         sampled_avg_control_r <= 3'b000;
         average_counter_r     <= 5'd1;
         average_sum_r         <= 5'd0;
         data_register_r       <= 10'd512;  // Fixed: 2^9 = 512 for 10-bit
         conv_finished_r       <= 1'b0;
      end else begin
         result_out            <= next_result_w;
         shift_register_r      <= next_shift_register_w;
         sampled_avg_control_r <= next_sampled_avg_control_w;
         average_counter_r     <= next_average_counter_w;
         average_sum_r         <= next_average_sum_w;
         data_register_r       <= next_data_register_w;
         conv_finished_r       <= result_strobe_w; // Direct assign
      end
   end

   //*******************************
   //   Combinatorial Processes
   //*******************************
   assign sample_out               = is_sampling_w;
   assign sample_out_n             = ~is_sampling_w;
   assign enable_loop_out          = ~is_sampling_w;
   assign conv_finished_strobe_out = conv_finished_r;
   assign pswitch_out              = ~data_register_r;
   assign nswitch_out              = data_register_r;

   // Shift register logic
   assign next_shift_register_w = is_averaging_w ? shift_register_r :
                                  {shift_register_r[0], shift_register_r[MATRIX_BITS+NONBINARY_REDUNDANCY+1:1]};

   assign next_sampled_avg_control_w = is_sampling_w ? avg_control_in : sampled_avg_control_r;

   // Non-binary lookup table for 10-bit SAR ADC
   wire [MATRIX_BITS-1:0] nonbinary_value_w;
   assign nonbinary_value_w =
        (shift_register_r == 15'd8192) ? 10'd201 :  // 2^13
        (shift_register_r == 15'd4096) ? 10'd121 :  // 2^12
        (shift_register_r == 15'd2048) ? 10'd74  :  // 2^11
        (shift_register_r == 15'd1024) ? 10'd45  :  // 2^10
        (shift_register_r == 15'd512 ) ? 10'd27  :  // 2^9
        (shift_register_r == 15'd256 ) ? 10'd17  :  // 2^8
        (shift_register_r == 15'd128 ) ? 10'd10  :  // 2^7
        (shift_register_r == 15'd64  ) ? 10'd6   :  // 2^6
        (shift_register_r == 15'd32  ) ? 10'd4   :  // 2^5
        (shift_register_r == 15'd16  ) ? 10'd2   :  // 2^4
        (shift_register_r == 15'd8   ) ? 10'd1   :  // 2^3
        (shift_register_r == 15'd4   ) ? 10'd1   :  // 2^2
        (shift_register_r == 15'd2   ) ? 10'd1   :  // 2^1
        (shift_register_r == 15'd1   ) ? 10'd1   :  // 2^0
        10'd0;

   // SAR update logic
   wire [MATRIX_BITS-1:0] sar_up   = data_register_r + nonbinary_value_w;
   wire [MATRIX_BITS-1:0] sar_down = data_register_r - nonbinary_value_w;

   assign next_data_register_w = is_sampling_w | is_holding_result_w | result_ready_w ? 10'd512 :
                                 is_averaging_w ? data_register_r :
                                 averaged_comparator_in_w ? sar_up : sar_down;

   // Final result assignment
   assign next_result_w = result_ready_w ?
                         (averaged_comparator_in_w ? data_register_r : data_register_r - 1) :
                         result_out;

   // Averaging logic
   assign next_average_counter_w = is_averaging_w ? average_counter_r + 1 : 5'd1;
   assign next_average_sum_w     = is_averaging_w ? average_sum_r + {4'b0, comparator_in} : {4'b0, comparator_in};

   assign averaged_comparator_in_w = (~lsb_region_w) ? comparator_in :
                                     is_averaging_w ? 1'b0 :
                                     (average_count_limit_w == 5'd3)  ? average_sum_r[1] :
                                     (average_count_limit_w == 5'd7)  ? average_sum_r[2] :
                                     (average_count_limit_w == 5'd15) ? average_sum_r[3] :
                                     (average_count_limit_w == 5'd31) ? average_sum_r[4] :
                                     comparator_in;

   // Averaging count limit
   assign average_count_limit_w = (sampled_avg_control_r == 3'b001) ? 5'd3  :
                                  (sampled_avg_control_r == 3'b010) ? 5'd7  :
                                  (sampled_avg_control_r == 3'b011) ? 5'd15 :
                                  (sampled_avg_control_r == 3'b100) ? 5'd31 :
                                  5'd1;

endmodule

sar_code_logic_custom/tb/adc_control_nonbinary_tb.v
//  Copyright 2022 Manuel Moser
//
//   Licensed under the Apache License, Version 2.0 (the "License");
//   you may not use this file except in compliance with the License.
//   You may obtain a copy of the License at
//
//       http://www.apache.org/licenses/LICENSE-2.0
//
//   Unless required by applicable law or agreed to in writing, software
//   distributed under the License is distributed on an "AS IS" BASIS,
//   WITHOUT WARRANTIES OR CONDITIONS OF ANY KIND, either express or implied.
//   See the License for the specific language governing permissions and
//   limitations under the License.

`include "adc_control_nonbinary.v"
`timescale 10us/1us

module adc_control_nonbinary_tb;
  parameter MATRIX_BITS = 10;
  reg clk;
  reg nrst;
  reg comparator_in;
  reg [2:0] avg_control;
  wire sample;
  wire nsample;
  wire enable;
  wire conv_finished;
  wire[MATRIX_BITS-1:0]  p_switch;
  wire[MATRIX_BITS-1:0]  n_switch;
  wire[MATRIX_BITS-1:0]  result;

  adc_control_nonbinary testmodule (
	   .clk(clk),
	   .rst_n(nrst),
	   .comparator_in(comparator_in),
	   .avg_control_in(avg_control),
	   .sample_out(sample),
	   .sample_out_n(nsample),
	   .enable_loop_out(enable),
	   .conv_finished_strobe_out(conv_finished),
	   .pswitch_out(p_switch),
	   .nswitch_out(n_switch),
	   .result_out(result)
	   );	

   initial begin
   	$dumpfile("dump.vcd");
   	$dumpvars(0,
   		clk,
   		nrst,
   		comparator_in,
   		avg_control,
   		sample,
   		nsample,
   		enable,
   		conv_finished,
   		p_switch,
   		n_switch,
   		result,
   		testmodule);
   end
   
   initial begin
   	#1 nrst=1;
    #1 nrst=0;
    #1 nrst=1;
    #1 nrst=1; avg_control = 3'b001;
    #1 comparator_in = 0;

    // first value is 064C
    avg_control = 3'b001; //4x averaging    
    #2 comparator_in = 0; //0001 +2048
    #2 comparator_in = 1; //8000 +806
    #2 comparator_in = 0; //4000 -486
    #2 comparator_in = 0; //2000 -295
    #2 comparator_in = 0; //1000 -180
    #2 comparator_in = 0; //0800 -110
    #2 comparator_in = 0; //0400 -67
    #2 comparator_in = 0; //0200 -41
    #2 comparator_in = 0; //0100 -25
    #2 comparator_in = 0; //0080 -15
    #2 comparator_in = 0; //0040 -9
    #2 comparator_in = 0; //0020 -6
    //averaging
    #2 comparator_in = 0; //0010 -4
    #2 comparator_in = 0;
    #2 comparator_in = 0;
    //averaging
    #2 comparator_in = 0; //0008 -2
    #2 comparator_in = 0;
    #2 comparator_in = 0;
    //averaging
    #2 comparator_in = 0; //0004 -1
    #2 comparator_in = 0;
    #2 comparator_in = 0;
    //averaging
    #2 comparator_in = 0; //0002 -1
    #2 comparator_in = 0;
    #2 comparator_in = 0;

    #2 comparator_in = 0; // hold_data_for_osr clock gating
        

    // second value is d3CC
    avg_control = 3'b000; //0x averaging
    #2 comparator_in = 0; //0001 +2048
    #2 comparator_in = 0; //8000 -806
    #2 comparator_in = 1; //4000 +486
    #2 comparator_in = 0; //2000 -295
    #2 comparator_in = 0; //1000 -180
    #2 comparator_in = 0; //0800 -110
    #2 comparator_in = 0; //0400 -67
    #2 comparator_in = 0; //0200 -41
    #2 comparator_in = 0; //0100 -25
    #2 comparator_in = 0; //0080 -15
    #2 comparator_in = 0; //0040 -9
    #2 comparator_in = 0; //0020 -6
    //averaging
    #2 comparator_in = 0; //0010 -4
    //averaging
    #2 comparator_in = 0; //0008 -2
    //averaging
    #2 comparator_in = 0; //0004 -1
    //averaging
    #2 comparator_in = 0; //0002 -1

    #2 comparator_in = 0; // hold_data_for_osr clock gating
    
    // third value is d15 0x0F
    avg_control = 3'b000; //0x averaging
    #2 comparator_in = 0; //0001 +2048
    #2 comparator_in = 0; //8000 -806
    #2 comparator_in = 0; //4000 -486
    #2 comparator_in = 0; //2000 -295
    #2 comparator_in = 0; //1000 -180
    #2 comparator_in = 0; //0800 -110
    #2 comparator_in = 0; //0400 -67
    #2 comparator_in = 0; //0200 -41
    #2 comparator_in = 0; //0100 -25
    #2 comparator_in = 0; //0080 -15
    #2 comparator_in = 0; //0040 -9
    #2 comparator_in = 0; //0020 -6
    //averaging
    #2 comparator_in = 1; //0010 +4
    //averaging
    #2 comparator_in = 1; //0008 +2
    //averaging
    #2 comparator_in = 1; //0004 +1
    //averaging
    #2 comparator_in = 1; //0002 +0


    #2 comparator_in = 0; // hold_data_for_osr clock gating

    // fourth value is 0x251 593
    avg_control = 3'b010; //8x averaging
    #2 comparator_in = 0; //0001 +2048
    #2 comparator_in = 0; //8000 -806
    #2 comparator_in = 0; //4000 -486
    #2 comparator_in = 1; //2000 +295
    #2 comparator_in = 0; //1000 -180
    #2 comparator_in = 0; //0800 -110
    #2 comparator_in = 0; //0400 -67
    #2 comparator_in = 0; //0200 -41
    #2 comparator_in = 0; //0100 -25
    #2 comparator_in = 0; //0080 -15
    #2 comparator_in = 0; //0040 -9
    #2 comparator_in = 0; //0020 -6
    //averaging
    #2 comparator_in = 0; //0010 -1
    #2 comparator_in = 1; 
    #2 comparator_in = 0; 
    #2 comparator_in = 1; 
    #2 comparator_in = 0; 
    #2 comparator_in = 0; 
    #2 comparator_in = 0; 
    //averaging
    #2 comparator_in = 0; //0008 -2
    #2 comparator_in = 0; 
    #2 comparator_in = 0;
    #2 comparator_in = 0; 
    #2 comparator_in = 0; 
    #2 comparator_in = 0; 
    #2 comparator_in = 1; 
    //averaging
    #2 comparator_in = 1; //0010 +1
    #2 comparator_in = 0; 
    #2 comparator_in = 0;
    #2 comparator_in = 1; 
    #2 comparator_in = 0; 
    #2 comparator_in = 1; 
    #2 comparator_in = 1; 
    //averaging
    #2 comparator_in = 1; //0010 +0
    #2 comparator_in = 1; 
    #2 comparator_in = 1; 
    #2 comparator_in = 1; 
    #2 comparator_in = 1; 
    #2 comparator_in = 1; 
    #2 comparator_in = 1; 
    
    #2 comparator_in = 0; // hold_data_for_osr clock gating

    // fifth value is max value with max averaging d4095
    avg_control = 3'b100; //0x averaging
    #2 comparator_in = 0; //0001
    #2 comparator_in = 1; //8000
    #2 comparator_in = 1; //4000
    #2 comparator_in = 1; //2000
    #2 comparator_in = 1; //1000
    #2 comparator_in = 1; //0800
    #2 comparator_in = 1; //0400
    #2 comparator_in = 1; //0200
    #2 comparator_in = 1; //0100
    #2 comparator_in = 1; //0080
    #2 comparator_in = 1; //0040
    #2 comparator_in = 1; //0020
    //averaging
    #2 comparator_in = 1; //0010
    #2 comparator_in = 1; 
    #2 comparator_in = 1; 
    #2 comparator_in = 1; 
    #2 comparator_in = 1; 
    #2 comparator_in = 1; 
    #2 comparator_in = 1; 
    #2 comparator_in = 1; 
    #2 comparator_in = 1; 
    #2 comparator_in = 1; 
    #2 comparator_in = 1; 
    #2 comparator_in = 1; 
    #2 comparator_in = 1; 
    #2 comparator_in = 1; 
    #2 comparator_in = 1; 
    #2 comparator_in = 1; 
    #2 comparator_in = 1; 
    #2 comparator_in = 1; 
    #2 comparator_in = 1; 
    #2 comparator_in = 1; 
    #2 comparator_in = 1; 
    #2 comparator_in = 1; 
    #2 comparator_in = 1; 
    #2 comparator_in = 1; 
    #2 comparator_in = 1; 
    #2 comparator_in = 1; 
    #2 comparator_in = 1; 
    #2 comparator_in = 1; 
    #2 comparator_in = 1; 
    #2 comparator_in = 1; 
    #2 comparator_in = 1; 
    //averaging
    #2 comparator_in = 1; //0008
    #2 comparator_in = 1; 
    #2 comparator_in = 1; 
    #2 comparator_in = 1; 
    #2 comparator_in = 1; 
    #2 comparator_in = 1; 
    #2 comparator_in = 1; 
    #2 comparator_in = 1; 
    #2 comparator_in = 1; 
    #2 comparator_in = 1; 
    #2 comparator_in = 1; 
    #2 comparator_in = 1; 
    #2 comparator_in = 1; 
    #2 comparator_in = 1; 
    #2 comparator_in = 1; 
    #2 comparator_in = 1; 
    #2 comparator_in = 1; 
    #2 comparator_in = 1; 
    #2 comparator_in = 1; 
    #2 comparator_in = 1; 
    #2 comparator_in = 1; 
    #2 comparator_in = 1; 
    #2 comparator_in = 1; 
    #2 comparator_in = 1; 
    #2 comparator_in = 1; 
    #2 comparator_in = 1; 
    #2 comparator_in = 1; 
    #2 comparator_in = 1; 
    #2 comparator_in = 1; 
    #2 comparator_in = 1; 
    #2 comparator_in = 1; 
    //averaging
    #2 comparator_in = 1; //0004
    #2 comparator_in = 1; 
    #2 comparator_in = 1; 
    #2 comparator_in = 1; 
    #2 comparator_in = 1; 
    #2 comparator_in = 1; 
    #2 comparator_in = 1; 
    #2 comparator_in = 1; 
    #2 comparator_in = 1; 
    #2 comparator_in = 1; 
    #2 comparator_in = 1; 
    #2 comparator_in = 1; 
    #2 comparator_in = 1; 
    #2 comparator_in = 1; 
    #2 comparator_in = 1; 
    #2 comparator_in = 1; 
    #2 comparator_in = 1; 
    #2 comparator_in = 1; 
    #2 comparator_in = 1; 
    #2 comparator_in = 1; 
    #2 comparator_in = 1; 
    #2 comparator_in = 1; 
    #2 comparator_in = 1; 
    #2 comparator_in = 1; 
    #2 comparator_in = 1; 
    #2 comparator_in = 1; 
    #2 comparator_in = 1; 
    #2 comparator_in = 1; 
    #2 comparator_in = 1; 
    #2 comparator_in = 1; 
    #2 comparator_in = 1; 
    //averaging
    #2 comparator_in = 1; //0002
    #2 comparator_in = 1; 
    #2 comparator_in = 1; 
    #2 comparator_in = 1; 
    #2 comparator_in = 1; 
    #2 comparator_in = 1; 
    #2 comparator_in = 1; 
    #2 comparator_in = 1; 
    #2 comparator_in = 1; 
    #2 comparator_in = 1; 
    #2 comparator_in = 1; 
    #2 comparator_in = 1; 
    #2 comparator_in = 1; 
    #2 comparator_in = 1; 
    #2 comparator_in = 1; 
    #2 comparator_in = 1; 
    #2 comparator_in = 1; 
    #2 comparator_in = 1; 
    #2 comparator_in = 1; 
    #2 comparator_in = 1; 
    #2 comparator_in = 1; 
    #2 comparator_in = 1; 
    #2 comparator_in = 1; 
    #2 comparator_in = 1; 
    #2 comparator_in = 1; 
    #2 comparator_in = 1; 
    #2 comparator_in = 1; 
    #2 comparator_in = 1; 
    #2 comparator_in = 1; 
    #2 comparator_in = 1; 
    #2 comparator_in = 1; 


    #2 comparator_in = 0; // hold_data_for_osr clock gating

    //  sixth value zero without averaging
    avg_control = 3'b000; //0x averaging
    #2 comparator_in = 0; //0001
    #2 comparator_in = 0; //8000
    #2 comparator_in = 0; //4000
    #2 comparator_in = 0; //2000
    #2 comparator_in = 0; //1000
    #2 comparator_in = 0; //0800
    #2 comparator_in = 0; //0400
    #2 comparator_in = 0; //0200
    #2 comparator_in = 0; //0100
    #2 comparator_in = 0; //0080
    #2 comparator_in = 0; //0040
    #2 comparator_in = 0; //0020
    //averaging
    #2 comparator_in = 0; //0010
    //averaging
    #2 comparator_in = 0; //0008
    //averaging
    #2 comparator_in = 0; //0004
    //averaging
    #2 comparator_in = 0; //0002

    #2 comparator_in = 0; // hold_data_for_osr clock gating

    #512 $finish;
   end

    initial begin
   	#1 clk=0;
    #6 clk=0;
    forever begin
    	#1 clk = ~clk;
    end
    end  


endmodule

verilog/dump.vcd
$date
	Mon Aug 11 08:45:00 2025
$end
$version
	Icarus Verilog
$end
$timescale
	1us
$end
$scope module adc_control_nonbinary_tb $end
$var reg 1 ! clk $end
$upscope $end
$scope module adc_control_nonbinary_tb $end
$var reg 1 " nrst $end
$upscope $end
$scope module adc_control_nonbinary_tb $end
$var reg 1 # comparator_in $end
$upscope $end
$scope module adc_control_nonbinary_tb $end
$var reg 3 $ avg_control [2:0] $end
$upscope $end
$scope module adc_control_nonbinary_tb $end
$var wire 1 % sample $end
$upscope $end
$scope module adc_control_nonbinary_tb $end
$var wire 1 & nsample $end
$upscope $end
$scope module adc_control_nonbinary_tb $end
$var wire 1 ' enable $end
$upscope $end
$scope module adc_control_nonbinary_tb $end
$var wire 1 ( conv_finished $end
$upscope $end
$scope module adc_control_nonbinary_tb $end
$var wire 10 ) p_switch [9:0] $end
$upscope $end
$scope module adc_control_nonbinary_tb $end
$var wire 10 * n_switch [9:0] $end
$upscope $end
$scope module adc_control_nonbinary_tb $end
$var wire 10 + result [9:0] $end
$upscope $end
$scope module adc_control_nonbinary_tb $end
$scope module testmodule $end
$var wire 3 , avg_control_in [2:0] $end
$var wire 1 ! clk $end
$var wire 1 # comparator_in $end
$var wire 1 ( conv_finished_strobe_out $end
$var wire 1 ' enable_loop_out $end
$var wire 1 - is_averaging_w $end
$var wire 1 . lsb_region_w $end
$var wire 10 / nswitch_out [9:0] $end
$var wire 10 0 pswitch_out [9:0] $end
$var wire 1 1 result_ready_w $end
$var wire 1 2 result_strobe_w $end
$var wire 1 " rst_n $end
$var wire 1 % sample_out $end
$var wire 1 & sample_out_n $end
$var wire 10 3 sar_up [9:0] $end
$var wire 10 4 sar_down [9:0] $end
$var wire 10 5 nonbinary_value_w [9:0] $end
$var wire 15 6 next_shift_register_w [14:0] $end
$var wire 3 7 next_sampled_avg_control_w [2:0] $end
$var wire 10 8 next_result_w [9:0] $end
$var wire 10 9 next_data_register_w [9:0] $end
$var wire 5 : next_average_sum_w [4:0] $end
$var wire 5 ; next_average_counter_w [4:0] $end
$var wire 1 < is_sampling_w $end
$var wire 1 = is_holding_result_w $end
$var wire 1 > averaged_comparator_in_w $end
$var wire 5 ? average_count_limit_w [4:0] $end
$var reg 5 @ average_counter_r [4:0] $end
$var reg 5 A average_sum_r [4:0] $end
$var reg 1 B conv_finished_r $end
$var reg 10 C data_register_r [9:0] $end
$var reg 10 D result_out [9:0] $end
$var reg 3 E sampled_avg_control_r [2:0] $end
$var reg 15 F shift_register_r [14:0] $end
$upscope $end
$upscope $end
$enddefinitions $end
#0
$dumpvars
bx F
bx E
bx D
bx C
xB
bx A
bx @
bx1 ?
x>
x=
x<
bx ;
bx :
bx 9
bx 8
bx 7
bx 6
b0xxxxxxxx 5
bx 4
bx 3
x2
x1
bx 0
bx /
x.
x-
bx ,
bx +
bx *
bx )
x(
x'
x&
x%
bx $
x#
x"
x!
$end
#10
0!
1"
#20
b0 8
b1000000000 9
b0x :
0.
01
02
0-
0'
0&
b100000000000000 6
b111111111 )
b111111111 0
b1 ;
b1 ?
0=
1%
1<
b1000000001 3
b111111111 4
b1 5
0(
0B
b1000000000 *
b1000000000 /
b1000000000 C
b0 A
b1 @
b0 E
b1 F
b0 +
b0 D
0"
#30
1"
#40
b1 7
b1 $
b1 ,
#50
b0 :
0>
0#
#80
b1000000000 3
b1000000000 4
b0 5
b1000000000 9
1'
1&
b10000000000000 6
b11 ?
0%
0<
b1 E
b100000000000000 F
1!
#90
b1 :
1>
0!
1#
#100
b1011001001 9
b1000000000000 6
b1011001001 3
b100110111 4
b11001001 5
b1 A
b10000000000000 F
1!
#110
b100110111 9
b0 :
0>
0!
0#
#120
b10111110 9
b100000000000 6
b1011001000 )
b1011001000 0
b1111001 5
b110110000 3
b10111110 4
b100110111 *
b100110111 /
b100110111 C
b0 A
b1000000000000 F
1!
#130
0!
#140
b1110100 9
b10000000000 6
b1001010 5
b1101000001 )
b1101000001 0
b100001000 3
b1110100 4
b10111110 *
b10111110 /
b10111110 C
b100000000000 F
1!
#150
0!
#160
b1000111 9
b101101 5
b1000000000 6
b1110001011 )
b1110001011 0
b10100001 3
b1000111 4
b1110100 *
b1110100 /
b1110100 C
b10000000000 F
1!
#170
0!
#180
b11011 5
b101100 9
b100000000 6
b1110111000 )
b1110111000 0
b1100010 3
b101100 4
b1000111 *
b1000111 /
b1000111 C
b1000000000 F
1!
#190
0!
#200
b10001 5
b11011 9
b10000000 6
b1111010011 )
b1111010011 0
b111101 3
b11011 4
b101100 *
b101100 /
b101100 C
b100000000 F
1!
#210
0!
#220
b1010 5
b10001 9
b1000000 6
b1111100100 )
b1111100100 0
b100101 3
b10001 4
b11011 *
b11011 /
b11011 C
b10000000 F
1!
#230
0!
#240
b110 5
b1011 9
b100000 6
b1111101110 )
b1111101110 0
b10111 3
b1011 4
b10001 *
b10001 /
b10001 C
b1000000 F
1!
#250
0!
#260
b100 5
b111 9
b10000 6
b1111110100 )
b1111110100 0
b1111 3
b111 4
b1011 *
b1011 /
b1011 C
b100000 F
1!
#270
0!
#280
b10 5
b10 ;
b111 9
1-
1.
b10000 6
b1111111000 )
b1111111000 0
b1001 3
b101 4
b111 *
b111 /
b111 C
b10000 F
1!
#290
0!
#300
b11 ;
b10 @
1!
#310
0!
#320
b101 9
b1000 6
0-
b1 ;
b11 @
1!
#330
0!
#340
b1 5
b101 9
b1000 6
b10 ;
1.
b1111111010 )
b1111111010 0
1-
b110 3
b100 4
b101 *
b101 /
b101 C
b1 @
b1000 F
1!
#350
0!
#360
b11 ;
b10 @
1!
#370
0!
#380
b100 9
b100 6
0-
b1 ;
b11 @
1!
#390
0!
#400
b10 ;
b1111111011 )
b1111111011 0
1-
b101 3
b11 4
b100 *
b100 /
b100 C
b1 @
b100 F
1!
#410
0!
#420
b11 ;
b10 @
1!
#430
0!
#440
b11 8
11
b1000000000 9
b10 6
0-
b1 ;
b11 @
1!
#450
0!
#460
12
b1 6
0.
01
b11 8
b1 ;
b111111111 )
b111111111 0
0-
1=
b1000000001 3
b111111111 4
b1000000000 *
b1000000000 /
b1000000000 C
b1 @
b10 F
b11 +
b11 D
1!
#470
0!
#480
02
0'
0&
b100000000000000 6
0=
1%
1<
1(
1B
b1 F
1!
#490
0!
#500
b1000000000 3
b1000000000 4
b0 5
b1000000000 9
1'
1&
b10000000000000 6
0%
0<
0(
0B
b100000000000000 F
1!
#510
0!
#520
b100110111 9
b1000000000000 6
b1011001001 3
b100110111 4
b11001001 5
b10000000000000 F
1!
#530
0!
#540
b10111110 9
b100000000000 6
b1011001000 )
b1011001000 0
b1111001 5
b110110000 3
b10111110 4
b100110111 *
b100110111 /
b100110111 C
b1000000000000 F
1!
#550
0!
b0 $
b0 ,
#560
b1110100 9
b10000000000 6
b1001010 5
b1101000001 )
b1101000001 0
b100001000 3
b1110100 4
b10111110 *
b10111110 /
b10111110 C
b100000000000 F
1!
#570
0!
#580
b1000111 9
b101101 5
b1000000000 6
b1110001011 )
b1110001011 0
b10100001 3
b1000111 4
b1110100 *
b1110100 /
b1110100 C
b10000000000 F
1!
#590
0!
#600
b11011 5
b101100 9
b100000000 6
b1110111000 )
b1110111000 0
b1100010 3
b101100 4
b1000111 *
b1000111 /
b1000111 C
b1000000000 F
1!
#610
b1100010 9
b1 :
1>
0!
1#
#620
b10001 5
b1110011 9
b10000000 6
b1110011101 )
b1110011101 0
b1110011 3
b1010001 4
b1100010 *
b1100010 /
b1100010 C
b1 A
b100000000 F
1!
#630
b1010001 9
b0 :
0>
0!
0#
#640
b1010 5
b1000111 9
b1000000 6
b1110101110 )
b1110101110 0
b1011011 3
b1000111 4
b1010001 *
b1010001 /
b1010001 C
b0 A
b10000000 F
1!
#650
0!
#660
b110 5
b1000001 9
b100000 6
b1110111000 )
b1110111000 0
b1001101 3
b1000001 4
b1000111 *
b1000111 /
b1000111 C
b1000000 F
1!
#670
0!
#680
b100 5
b111101 9
b10000 6
b1110111110 )
b1110111110 0
b1000101 3
b111101 4
b1000001 *
b1000001 /
b1000001 C
b100000 F
1!
#690
0!
#700
b10 5
b10 ;
b111101 9
1-
1.
b10000 6
b1111000010 )
b1111000010 0
b111111 3
b111011 4
b111101 *
b111101 /
b111101 C
b10000 F
1!
#710
0!
#720
b11 ;
b10 @
1!
#730
0!
#740
b111011 9
b1000 6
0-
b1 ;
b11 @
1!
#750
0!
#760
b1 5
b111011 9
b1000 6
b10 ;
1.
b1111000100 )
b1111000100 0
1-
b111100 3
b111010 4
b111011 *
b111011 /
b111011 C
b1 @
b1000 F
1!
#770
0!
#780
b11 ;
b10 @
1!
#790
0!
#800
b111010 9
b100 6
0-
b1 ;
b11 @
1!
#810
0!
#820
b10 ;
b1111000101 )
b1111000101 0
1-
b111011 3
b111001 4
b111010 *
b111010 /
b111010 C
b1 @
b100 F
1!
#830
0!
#840
b11 ;
b10 @
1!
#850
0!
#860
b111001 8
11
b1000000000 9
b10 6
0-
b1 ;
b11 @
1!
#870
0!
#880
12
b1 6
0.
01
b111001 8
b1 ;
b111111111 )
b111111111 0
0-
1=
b1000000001 3
b111111111 4
b1000000000 *
b1000000000 /
b1000000000 C
b1 @
b10 F
b111001 +
b111001 D
1!
#890
0!
#900
02
b0 7
0'
0&
b100000000000000 6
0=
1%
1<
1(
1B
b1 F
1!
#910
0!
#920
b1000000000 3
b1000000000 4
b0 5
b1000000000 9
1'
1&
b10000000000000 6
b1 ?
0%
0<
0(
0B
b0 E
b100000000000000 F
1!
#930
0!
#940
b100110111 9
b1000000000000 6
b1011001001 3
b100110111 4
b11001001 5
b10000000000000 F
1!
#950
0!
#960
b10111110 9
b100000000000 6
b1011001000 )
b1011001000 0
b1111001 5
b110110000 3
b10111110 4
b100110111 *
b100110111 /
b100110111 C
b1000000000000 F
1!
#970
0!
#980
b1110100 9
b10000000000 6
b1001010 5
b1101000001 )
b1101000001 0
b100001000 3
b1110100 4
b10111110 *
b10111110 /
b10111110 C
b100000000000 F
1!
#990
0!
#1000
b1000111 9
b101101 5
b1000000000 6
b1110001011 )
b1110001011 0
b10100001 3
b1000111 4
b1110100 *
b1110100 /
b1110100 C
b10000000000 F
1!
#1010
0!
#1020
b11011 5
b101100 9
b100000000 6
b1110111000 )
b1110111000 0
b1100010 3
b101100 4
b1000111 *
b1000111 /
b1000111 C
b1000000000 F
1!
#1030
0!
#1040
b10001 5
b11011 9
b10000000 6
b1111010011 )
b1111010011 0
b111101 3
b11011 4
b101100 *
b101100 /
b101100 C
b100000000 F
1!
#1050
0!
#1060
b1010 5
b10001 9
b1000000 6
b1111100100 )
b1111100100 0
b100101 3
b10001 4
b11011 *
b11011 /
b11011 C
b10000000 F
1!
#1070
0!
#1080
b110 5
b1011 9
b100000 6
b1111101110 )
b1111101110 0
b10111 3
b1011 4
b10001 *
b10001 /
b10001 C
b1000000 F
1!
#1090
0!
#1100
b100 5
b111 9
b10000 6
b1111110100 )
b1111110100 0
b1111 3
b111 4
b1011 *
b1011 /
b1011 C
b100000 F
1!
#1110
0!
#1120
b10 5
b101 9
1.
b1000 6
b1111111000 )
b1111111000 0
b1001 3
b101 4
b111 *
b111 /
b111 C
b10000 F
1!
#1130
0!
#1140
b1 5
b100 9
1.
b100 6
b1111111010 )
b1111111010 0
b110 3
b100 4
b101 *
b101 /
b101 C
b1000 F
1!
#1150
b110 9
1>
b1 :
0!
1#
#1160
b110 8
b1000000000 9
11
b10 6
b1111111001 )
b1111111001 0
b111 3
b101 4
b110 *
b110 /
b110 C
b1 A
b100 F
1!
#1170
0!
#1180
0.
01
12
b110 8
b1 6
b111111111 )
b111111111 0
1=
b1000000001 3
b111111111 4
b1000000000 *
b1000000000 /
b1000000000 C
b10 F
b110 +
b110 D
1!
#1190
0!
#1200
02
0'
0&
b100000000000000 6
0=
1%
1<
1(
1B
b1 F
1!
#1210
0!
#1220
b1000000000 3
b1000000000 4
b0 5
b1000000000 9
1'
1&
b10000000000000 6
0%
0<
0(
0B
b100000000000000 F
1!
#1230
b0 :
0>
0!
b10 $
b10 ,
0#
#1240
b100110111 9
b1000000000000 6
b1011001001 3
b100110111 4
b11001001 5
b0 A
b10000000000000 F
1!
#1250
0!
#1260
b10111110 9
b100000000000 6
b1011001000 )
b1011001000 0
b1111001 5
b110110000 3
b10111110 4
b100110111 *
b100110111 /
b100110111 C
b1000000000000 F
1!
#1270
0!
#1280
b1110100 9
b10000000000 6
b1001010 5
b1101000001 )
b1101000001 0
b100001000 3
b1110100 4
b10111110 *
b10111110 /
b10111110 C
b100000000000 F
1!
#1290
0!
#1300
b1000111 9
b101101 5
b1000000000 6
b1110001011 )
b1110001011 0
b10100001 3
b1000111 4
b1110100 *
b1110100 /
b1110100 C
b10000000000 F
1!
#1310
b10100001 9
b1 :
1>
0!
1#
